pi_dawn/__init__.py
pi_dawn/comm.py
pi_dawn/daemon.py
pi_dawn/gamma_test.py
pi_dawn/graphics.py
pi_dawn/model.py
pi_dawn/templates.py
pi_dawn/frontend/.gitignore
pi_dawn/frontend/README.md
pi_dawn/frontend/babel.config.js
pi_dawn/frontend/package-lock.json
pi_dawn/frontend/package.json
pi_dawn/frontend/vue.config.js
pi_dawn/frontend/dist/index.html
pi_dawn/frontend/dist/static/favicon-32x32.png
pi_dawn/frontend/dist/static/favicon.ico
pi_dawn/frontend/dist/static/icon-144x144.png
pi_dawn/frontend/dist/static/icon-168x168.png
pi_dawn/frontend/dist/static/icon-192x192.png
pi_dawn/frontend/dist/static/icon-48x48.png
pi_dawn/frontend/dist/static/icon-72x72.png
pi_dawn/frontend/dist/static/icon-96x96.png
pi_dawn/frontend/dist/static/manifest.json
pi_dawn/frontend/dist/static/css/app.42e8be52.css
pi_dawn/frontend/dist/static/css/chunk-vendors.31ac1ac0.css
pi_dawn/frontend/dist/static/fonts/materialicons-72f23bfc9fd8dc16d72119a9e402e18b721f851d.0b77ec49.woff
pi_dawn/frontend/dist/static/fonts/roboto-934014cc9bbe5883542be756b3146c05844b254f.bafb105b.woff
pi_dawn/frontend/dist/static/fonts/roboto-b2198c3fc1c72646d372f63e135e70ba2c9fed8e.cf6613d1.woff
pi_dawn/frontend/dist/static/fonts/roboto-f549f1fe8a0b86ef3fbdcb8d508440aff84c385c.de8b7431.woff
pi_dawn/frontend/dist/static/fonts/roboto-ff5673d89e6c2893d24c87bc9786c632290e150e.a1471d1d.woff
pi_dawn/frontend/dist/static/js/app.5947a961.js
pi_dawn/frontend/dist/static/js/app.5947a961.js.map
pi_dawn/frontend/dist/static/js/chunk-vendors.b8719082.js
pi_dawn/frontend/dist/static/js/chunk-vendors.b8719082.js.map
pi_dawn/frontend/public/index.html
pi_dawn/frontend/public/static/favicon-32x32.png
pi_dawn/frontend/public/static/favicon.ico
pi_dawn/frontend/public/static/icon-144x144.png
pi_dawn/frontend/public/static/icon-168x168.png
pi_dawn/frontend/public/static/icon-192x192.png
pi_dawn/frontend/public/static/icon-48x48.png
pi_dawn/frontend/public/static/icon-72x72.png
pi_dawn/frontend/public/static/icon-96x96.png
pi_dawn-1.0.dist-info/COPYING
pi_dawn-1.0.dist-info/METADATA
pi_dawn-1.0.dist-info/WHEEL
pi_dawn-1.0.dist-info/entry_points.txt
pi_dawn-1.0.dist-info/top_level.txt
pi_dawn-1.0.dist-info/RECORD
