Metadata-Version: 2.1
Name: pi-dawn
Version: 1.0
Summary: Pi Dawn
Home-page: https://github.com/sebasgo/pi-dawn
Author: Sebastian Gottfried
Author-email: sebastian.gottfried@posteo.de
License: UNKNOWN
Platform: UNKNOWN
Classifier: Development Status :: 3 - Alpha
Classifier: Environment :: Web Environment
Classifier: Framework :: Flask
Classifier: Intended Audience :: Developers
Classifier: License :: OSI Approved :: GNU General Public License v3 (GPLv3)
Classifier: Programming Language :: Python :: 3
Classifier: Programming Language :: Python :: 3.5
Classifier: Programming Language :: Python :: 3.6
Classifier: Programming Language :: Python :: 3.7
Requires-Dist: adafruit-ws2801
Requires-Dist: attrs
Requires-Dist: click
Requires-Dist: Flask
Requires-Dist: Flask-SQLAlchemy
Requires-Dist: redis
Provides-Extra: dev
Requires-Dist: check-manifest ; extra == 'dev'
Requires-Dist: pygame ; extra == 'dev'
